[{"content": "Distribute", "atti": "can", "recipient": "the software", "condInxs": []}, {"content": "Modify", "atti": "can", "recipient": "the software", "condInxs": []}, {"content": "Commercial Use", "atti": "cannot", "recipient": "", "condInxs": []}, {"content": "Hold Liable", "atti": "can", "recipient": "the software be", "condInxs": []}, {"content": "Include Copyright", "atti": "can", "recipient": "", "condInxs": []}, {"content": "Include License", "atti": "can", "recipient": "", "condInxs": []}, {"content": "Sublicense", "atti": "cannot", "recipient": "", "condInxs": []}, {"content": "Use Trademark", "atti": "cannot", "recipient": "", "condInxs": []}, {"content": "Private Use", "atti": "can", "recipient": "the software", "condInxs": []}, {"content": "Disclose Source", "atti": "can", "recipient": "", "condInxs": []}, {"content": "State Changes", "atti": "can", "recipient": "", "condInxs": []}, {"content": "Place Warranty", "atti": "cannot", "recipient": "", "condInxs": []}, {"content": "Include Notice", "atti": "can", "recipient": "", "condInxs": []}, {"content": "Include Original", "atti": "can", "recipient": "", "condInxs": []}, {"content": "Give Credit", "atti": "can", "recipient": "", "condInxs": []}, {"content": "Use Patent Claims", "atti": "cannot", "recipient": "", "condInxs": []}, {"content": "Rename", "atti": "can", "recipient": "", "condInxs": []}, {"content": "Relicense", "atti": "cannot", "recipient": "", "condInxs": []}, {"content": "Contact Author", "atti": "can", "recipient": "", "condInxs": []}, {"content": "Include Install Instructions", "atti": "can", "recipient": "", "condInxs": []}, {"content": "Compensate for Damages", "atti": "can", "recipient": "", "condInxs": []}, {"content": "Statically Link", "atti": "cannot", "recipient": "", "condInxs": []}, {"content": "Pay Above Use Threshold", "atti": "can", "recipient": "", "condInxs": []}]