[{"A": "objgraph-master/objgraph.py", "B": "objgraph-master/objgraph.py:tempfile"}, {"A": "objgraph-master/objgraph.py", "B": "objgraph-master/objgraph.py:graphviz"}, {"A": "objgraph-master/objgraph.py", "B": "objgraph-master/objgraph.py:__future__"}, {"A": "objgraph-master/objgraph.py", "B": "objgraph-master/objgraph.py:inspect"}, {"A": "objgraph-master/objgraph.py", "B": "objgraph-master/objgraph.py:re"}, {"A": "objgraph-master", "B": "objgraph-master/objgraph.py"}, {"A": "objgraph-master", "B": "objgraph-master/setup.py:doctest"}, {"A": "objgraph-master", "B": "objgraph-master/setup.py:re"}, {"A": "objgraph-master", "B": "objgraph-master/setup.py:setuptools"}, {"A": "objgraph-master", "B": "objgraph-master/tests.py:tempfile"}, {"A": "objgraph-master", "B": "objgraph-master/tests.py:textwrap"}, {"A": "objgraph-master", "B": "objgraph-master/tests.py:glob"}, {"A": "objgraph-master", "B": "objgraph-master/tests.py:mock"}, {"A": "objgraph-master", "B": "objgraph-master/tests.py:doctest"}, {"A": "objgraph-master", "B": "objgraph-master/tests.py:re"}, {"A": "objgraph-master", "B": "objgraph-master/docs/conf.py:re"}]